{
  "topology_id": 1,
  "netlist": "single_ended1",
  "simulation_id": 10,
  "operating_points": {
    "MM0": {
      "region_of_operation": 0.0,
      "gm": 5.19e-11,
      "ids": 1.36e-12,
      "vds": 0.549,
      "vgs": 0.0553
    },
    "MM1": {
      "region_of_operation": 0.0,
      "gm": 9.96e-11,
      "ids": 2.98e-12,
      "vds": 0.00774,
      "vgs": 0.00621
    },
    "MM2": {
      "region_of_operation": 0.0,
      "gm": 8.25e-11,
      "ids": 2.47e-12,
      "vds": 0.00621,
      "vgs": 0.00621
    },
    "MM3": {
      "region_of_operation": 0.0,
      "gm": 5.19e-11,
      "ids": 1.35e-12,
      "vds": 0.548,
      "vgs": 0.0553
    },
    "MM4": {
      "region_of_operation": 0.0,
      "gm": 5.12e-11,
      "ids": 1.38e-12,
      "vds": 0.445,
      "vgs": 0.0911
    },
    "MM5": {
      "region_of_operation": 1.0,
      "gm": 1.96e-11,
      "ids": 2.91e-12,
      "vds": 7.72e-10,
      "vgs": 0.653
    },
    "MM6": {
      "region_of_operation": 1.0,
      "gm": 1.6e-11,
      "ids": 2.4e-12,
      "vds": 6.28e-10,
      "vgs": 0.655
    }
  }
}